beginner_web/__init__.py
beginner_web-0.0.2.dist-info/LICENSE
beginner_web-0.0.2.dist-info/METADATA
beginner_web-0.0.2.dist-info/WHEEL
beginner_web-0.0.2.dist-info/top_level.txt
beginner_web-0.0.2.dist-info/RECORD
