Metadata-Version: 2.1
Name: beginner-web
Version: 0.0.2
Summary: Python package to let beginners in Python have their website more easily.
Home-page: https://github.com/Dreambuilder4028/coder/commit/e15128f3440ebba64523b68c1134251805bd2395
Author: Dreambuilder4028
Author-email: jiade_student@163.com
License: UNKNOWN
Platform: UNKNOWN
Classifier: Programming Language :: Python :: 3
Classifier: Operating System :: OS Independent
